nbipackager/__init__.py
nbipackager/cli.py
nbipackager/config.py
nbipackager/commands/__init__.py
nbipackager/commands/addpackage.py
nbipackager/commands/addtobundle.py
nbipackager/commands/findpackage.py
nbipackager/commands/makebundle.py
nbipackager/commands/scanpackages.py
nbipackager-0.0.3.dist-info/LICENSE
nbipackager-0.0.3.dist-info/METADATA
nbipackager-0.0.3.dist-info/WHEEL
nbipackager-0.0.3.dist-info/entry_points.txt
nbipackager-0.0.3.dist-info/top_level.txt
nbipackager-0.0.3.dist-info/RECORD
