Metadata-Version: 2.2
Name: nbipackager
Version: 0.0.3
Summary: A package manager for Singularity images
Author-email: Andrea Telatin <andrea.telatin@quadram.ac.uk>
License: MIT
Project-URL: Homepage, https://github.com/quadram-institute-bioscience/nbipackager
Project-URL: Documentation, https://github.com/quadram-institute-bioscience/nbipackager#readme
Project-URL: Repository, https://github.com/quadram-institute-bioscience/nbipackager.git
Project-URL: Bug Tracker, https://github.com/quadram-institute-bioscience/nbipackager/issues
Keywords: singularity,container,package-manager
Classifier: Development Status :: 3 - Alpha
Classifier: Intended Audience :: Science/Research
Classifier: License :: OSI Approved :: MIT License
Classifier: Programming Language :: Python :: 3
Classifier: Programming Language :: Python :: 3.6
Classifier: Programming Language :: Python :: 3.7
Classifier: Programming Language :: Python :: 3.8
Classifier: Programming Language :: Python :: 3.9
Classifier: Programming Language :: Python :: 3.10
Classifier: Topic :: Software Development :: Build Tools
Requires-Python: >=3.6
License-File: LICENSE
Requires-Dist: click>=8.0.0
Requires-Dist: configparser>=5.0.0
